TrimbleZebraPrinting/__init__.py
TrimbleZebraPrinting/trimble_graphics_conversion.py
TrimbleZebraPrinting/trimble_zebra_printing.py
TrimbleZebraPrinting-1.2.dist-info/LICENSE
TrimbleZebraPrinting-1.2.dist-info/METADATA
TrimbleZebraPrinting-1.2.dist-info/WHEEL
TrimbleZebraPrinting-1.2.dist-info/top_level.txt
TrimbleZebraPrinting-1.2.dist-info/RECORD
