Metadata-Version: 2.1
Name: TrimbleZebraPrinting
Version: 1.2
Summary: Trimble Zebra Printing was built to simplify and standardize ZPL printing in the Trimble Facilities. This includes features, such as DPI scaling, to improve printing automation. Upscaling DPI results in a loss of quality. Matching DPIs or downscaling is recommended.
Author-email: Ryan Strasburg <ryan_strasburg@trimble.com>
Project-URL: Homepage, https://github.com/ryan-strasburg/Trimble-Zebra-Printing
Project-URL: Bug Tracker, https://github.com/ryan-strasburg/Trimble-Zebra-Printing/issues
Classifier: Programming Language :: Python :: 3
Classifier: License :: OSI Approved :: MIT License
Classifier: Operating System :: Microsoft :: Windows
Requires-Python: >=3.7
License-File: LICENSE
Requires-Dist: Pillow (>=9.4.0)
Requires-Dist: pywin32 (>=306)
